napalm_netonix/__init__.py
napalm_netonix/netonix.py
napalm_netonix-0.0.3.dist-info/LICENSE
napalm_netonix-0.0.3.dist-info/METADATA
napalm_netonix-0.0.3.dist-info/WHEEL
napalm_netonix-0.0.3.dist-info/top_level.txt
napalm_netonix-0.0.3.dist-info/RECORD
