Metadata-Version: 2.1
Name: napalm-netonix
Version: 0.0.3
Summary: NAPALM module for Netonix WISP switches
Author-email: shrank <info@murxs.ch>
License: This is free and unencumbered software released into the public domain.
Project-URL: Homepage, https://github.com/shrank/napalm_netonix
Keywords: network,automation,netonix
Classifier: Programming Language :: Python :: 3
Classifier: Operating System :: OS Independent
Requires-Python: >=3.0
License-File: LICENSE
Requires-Dist: python-netonix-api
Requires-Dist: deepdiff
Requires-Dist: napalm
